MANIFEST.in
README.markdown
setup.py
smpp/__init__.py
smpp.twisted.egg-info/PKG-INFO
smpp.twisted.egg-info/SOURCES.txt
smpp.twisted.egg-info/dependency_links.txt
smpp.twisted.egg-info/not-zip-safe
smpp.twisted.egg-info/requires.txt
smpp.twisted.egg-info/top_level.txt
smpp/twisted/__init__.py
smpp/twisted/client.py
smpp/twisted/config.py
smpp/twisted/protocol.py
smpp/twisted/server.py
smpp/twisted/examples/__init__.py
smpp/twisted/examples/transceiver.py
smpp/twisted/tests/__init__.py
smpp/twisted/tests/smpp_client_test.py
smpp/twisted/tests/smpp_protocol_test.py
smpp/twisted/tests/smsc_simulator.py
smpp/twisted/tests/test_smpp_server.py