Metadata-Version: 1.0
Name: smpp.twisted
Version: 0.4
Summary: SMPP 3.4 client built on Twisted
Home-page: https://github.com/mozes/smpp.twisted
Author: Roger Hoover
Author-email: roger.hoover@gmail.com
License: Apache License 2.0
Keywords: smpp twisted
Platform: UNKNOWN
Classifier: Development Status :: 5 - Production/Stable
Classifier: Framework :: Twisted
Classifier: Topic :: System :: Networking
Classifier: Operating System :: OS Independent
Classifier: License :: OSI Approved :: Apache Software License
Classifier: Intended Audience :: Developers
Classifier: Programming Language :: Python
Classifier: Topic :: Software Development :: Libraries :: Python Modules
